repo_helper_sphinx_theme/static/custom.css
repo_helper_sphinx_theme/static/header.js
repo_helper_sphinx_theme/static/repo_helper.css_t
repo_helper_sphinx_theme/__init__.py
repo_helper_sphinx_theme/layout.html
repo_helper_sphinx_theme/relations.html
repo_helper_sphinx_theme/theme.conf
repo_helper_sphinx_theme-0.0.3.dist-info/LICENSE
repo_helper_sphinx_theme-0.0.3.dist-info/METADATA
repo_helper_sphinx_theme-0.0.3.dist-info/WHEEL
repo_helper_sphinx_theme-0.0.3.dist-info/entry_points.txt
repo_helper_sphinx_theme-0.0.3.dist-info/RECORD
