Metadata-Version: 2.1
Name: repo-helper-sphinx-theme
Version: 0.0.3
Summary: Sphinx Theme for repo_helper.
Author-email: Dominic Davis-Foster <dominic@davis-foster.co.uk>
License: BSD-3-Clause
Keywords: documentation,repo-helper,sphinx
Home-page: https://github.com/repo-helper/repo_helper_sphinx_theme
Project-URL: Issue Tracker, https://github.com/repo-helper/repo_helper_sphinx_theme/issues
Project-URL: Source Code, https://github.com/repo-helper/repo_helper_sphinx_theme
Project-URL: Documentation, https://repo-helper-sphinx-theme.readthedocs.io/en/latest
Platform: Windows
Platform: macOS
Platform: Linux
Classifier: Development Status :: 4 - Beta
Classifier: Environment :: Web Environment
Classifier: Framework :: Sphinx
Classifier: Framework :: Sphinx :: Theme
Classifier: Intended Audience :: Developers
Classifier: License :: OSI Approved :: BSD License
Classifier: Operating System :: OS Independent
Classifier: Programming Language :: Python
Classifier: Programming Language :: Python :: 3 :: Only
Classifier: Programming Language :: Python :: 3.6
Classifier: Programming Language :: Python :: 3.7
Classifier: Programming Language :: Python :: 3.8
Classifier: Programming Language :: Python :: 3.9
Classifier: Programming Language :: Python :: Implementation :: CPython
Classifier: Topic :: Documentation
Classifier: Topic :: Software Development :: Documentation
Classifier: Topic :: Utilities
Requires-Python: >=3.6
Requires-Dist: alabaster>=0.7.12
Requires-Dist: sphinx>=3.0.3
